{"otherData": {},"traceEvents":[{"cat":"function","dur":63071,"name":"glfwInit","ph":"X","pid":0,"tid":4177716615,"ts":93074282407},{"cat":"function","dur":840807,"name":"glfwCreateWindow","ph":"X","pid":0,"tid":4177716615,"ts":93074346808},{"cat":"function","dur":1110,"name":"void __cdecl Quelos::OpenGLContext::Init(void)","ph":"X","pid":0,"tid":4177716615,"ts":93075187803},{"cat":"function","dur":15,"name":"void __cdecl Quelos::WindowsWindow::SetVSync(bool)","ph":"X","pid":0,"tid":4177716615,"ts":93075189066},{"cat":"function","dur":906754,"name":"void __cdecl Quelos::WindowsWindow::Init(const struct Quelos::WindowProps &)","ph":"X","pid":0,"tid":4177716615,"ts":93074282406},{"cat":"function","dur":906817,"name":"__cdecl Quelos::WindowsWindow::WindowsWindow(const struct Quelos::WindowProps &)","ph":"X","pid":0,"tid":4177716615,"ts":93074282402},{"cat":"function","dur":899,"name":"void __cdecl Quelos::Input::Init(void)","ph":"X","pid":0,"tid":4177716615,"ts":93075189362},{"cat":"function","dur":26,"name":"__cdecl Quelos::OpenGLVertexArray::OpenGLVertexArray(void)","ph":"X","pid":0,"tid":4177716615,"ts":93075191985},{"cat":"function","dur":122,"name":"__cdecl Quelos::OpenGLVertexBuffer::OpenGLVertexBuffer(unsigned int)","ph":"X","pid":0,"tid":4177716615,"ts":93075192230},{"cat":"function","dur":0,"name":"void __cdecl Quelos::OpenGLVertexBuffer::Bind(void) const","ph":"X","pid":0,"tid":4177716615,"ts":93075192517},{"cat":"function","dur":113,"name":"void __cdecl Quelos::OpenGLVertexArray::AddVertexBuffer(const class std::shared_ptr<class Quelos::VertexBuffer> &)","ph":"X","pid":0,"tid":4177716615,"ts":93075192505},{"cat":"function","dur":2387,"name":"__cdecl Quelos::OpenGLIndexBuffer::OpenGLIndexBuffer(unsigned int *,unsigned int)","ph":"X","pid":0,"tid":4177716615,"ts":93075195769},{"cat":"function","dur":1,"name":"void __cdecl Quelos::OpenGLIndexBuffer::Bind(void) const","ph":"X","pid":0,"tid":4177716615,"ts":93075198327},{"cat":"function","dur":76,"name":"void __cdecl Quelos::OpenGLVertexArray::SetIndexBuffer(const class std::shared_ptr<class Quelos::IndexBuffer> &)","ph":"X","pid":0,"tid":4177716615,"ts":93075198319},{"cat":"function","dur":14,"name":"__cdecl Quelos::OpenGLVertexArray::OpenGLVertexArray(void)","ph":"X","pid":0,"tid":4177716615,"ts":93075198495},{"cat":"function","dur":127,"name":"__cdecl Quelos::OpenGLVertexBuffer::OpenGLVertexBuffer(unsigned int)","ph":"X","pid":0,"tid":4177716615,"ts":93075198583},{"cat":"function","dur":0,"name":"void __cdecl Quelos::OpenGLVertexBuffer::Bind(void) const","ph":"X","pid":0,"tid":4177716615,"ts":93075198853},{"cat":"function","dur":83,"name":"void __cdecl Quelos::OpenGLVertexArray::AddVertexBuffer(const class std::shared_ptr<class Quelos::VertexBuffer> &)","ph":"X","pid":0,"tid":4177716615,"ts":93075198847},{"cat":"function","dur":2,"name":"void __cdecl Quelos::OpenGLIndexBuffer::Bind(void) const","ph":"X","pid":0,"tid":4177716615,"ts":93075201671},{"cat":"function","dur":145,"name":"void __cdecl Quelos::OpenGLVertexArray::SetIndexBuffer(const class std::shared_ptr<class Quelos::IndexBuffer> &)","ph":"X","pid":0,"tid":4177716615,"ts":93075201663},{"cat":"function","dur":7,"name":"__cdecl Quelos::OpenGLVertexArray::OpenGLVertexArray(void)","ph":"X","pid":0,"tid":4177716615,"ts":93075201881},{"cat":"function","dur":122,"name":"__cdecl Quelos::OpenGLVertexBuffer::OpenGLVertexBuffer(unsigned int)","ph":"X","pid":0,"tid":4177716615,"ts":93075201958},{"cat":"function","dur":1,"name":"void __cdecl Quelos::OpenGLVertexBuffer::Bind(void) const","ph":"X","pid":0,"tid":4177716615,"ts":93075202206},{"cat":"function","dur":79,"name":"void __cdecl Quelos::OpenGLVertexArray::AddVertexBuffer(const class std::shared_ptr<class Quelos::VertexBuffer> &)","ph":"X","pid":0,"tid":4177716615,"ts":93075202201},{"cat":"function","dur":198,"name":"__cdecl Quelos::OpenGLTexture2D::OpenGLTexture2D(unsigned int,unsigned int)","ph":"X","pid":0,"tid":4177716615,"ts":93075204239},{"cat":"function","dur":93,"name":"void __cdecl Quelos::OpenGLTexture2D::SetData(void *,unsigned int)","ph":"X","pid":0,"tid":4177716615,"ts":93075204578},{"cat":"function","dur":498,"name":"class std::basic_string<char,struct std::char_traits<char>,class std::allocator<char> > __cdecl Quelos::OpenGLShader::ReadFile(const class std::basic_string<char,struct std::char_traits<char>,class std::allocator<char> > &)","ph":"X","pid":0,"tid":4177716615,"ts":93075205081},{"cat":"function","dur":123,"name":"class std::unordered_map<unsigned int,class std::basic_string<char,struct std::char_traits<char>,class std::allocator<char> >,struct std::hash<unsigned int>,struct std::equal_to<unsigned int>,class std::allocator<struct std::pair<unsigned int const ,class std::basic_string<char,struct std::char_traits<char>,class std::allocator<char> > > > > __cdecl Quelos::OpenGLShader::PreProcess(const class std::basic_string<char,struct std::char_traits<char>,class std::allocator<char> > &)","ph":"X","pid":0,"tid":4177716615,"ts":93075205681},{"cat":"function","dur":129391,"name":"__cdecl Quelos::OpenGLShader::OpenGLShader(const class std::basic_string<char,struct std::char_traits<char>,class std::allocator<char> > &)","ph":"X","pid":0,"tid":4177716615,"ts":93075204941},{"cat":"function","dur":199,"name":"class std::basic_string<char,struct std::char_traits<char>,class std::allocator<char> > __cdecl Quelos::OpenGLShader::ReadFile(const class std::basic_string<char,struct std::char_traits<char>,class std::allocator<char> > &)","ph":"X","pid":0,"tid":4177716615,"ts":93075334623},{"cat":"function","dur":68,"name":"class std::unordered_map<unsigned int,class std::basic_string<char,struct std::char_traits<char>,class std::allocator<char> >,struct std::hash<unsigned int>,struct std::equal_to<unsigned int>,class std::allocator<struct std::pair<unsigned int const ,class std::basic_string<char,struct std::char_traits<char>,class std::allocator<char> > > > > __cdecl Quelos::OpenGLShader::PreProcess(const class std::basic_string<char,struct std::char_traits<char>,class std::allocator<char> > &)","ph":"X","pid":0,"tid":4177716615,"ts":93075334914},{"cat":"function","dur":52805,"name":"__cdecl Quelos::OpenGLShader::OpenGLShader(const class std::basic_string<char,struct std::char_traits<char>,class std::allocator<char> > &)","ph":"X","pid":0,"tid":4177716615,"ts":93075334514},{"cat":"function","dur":178,"name":"class std::basic_string<char,struct std::char_traits<char>,class std::allocator<char> > __cdecl Quelos::OpenGLShader::ReadFile(const class std::basic_string<char,struct std::char_traits<char>,class std::allocator<char> > &)","ph":"X","pid":0,"tid":4177716615,"ts":93075387594},{"cat":"function","dur":55,"name":"class std::unordered_map<unsigned int,class std::basic_string<char,struct std::char_traits<char>,class std::allocator<char> >,struct std::hash<unsigned int>,struct std::equal_to<unsigned int>,class std::allocator<struct std::pair<unsigned int const ,class std::basic_string<char,struct std::char_traits<char>,class std::allocator<char> > > > > __cdecl Quelos::OpenGLShader::PreProcess(const class std::basic_string<char,struct std::char_traits<char>,class std::allocator<char> > &)","ph":"X","pid":0,"tid":4177716615,"ts":93075387851},{"cat":"function","dur":43023,"name":"__cdecl Quelos::OpenGLShader::OpenGLShader(const class std::basic_string<char,struct std::char_traits<char>,class std::allocator<char> > &)","ph":"X","pid":0,"tid":4177716615,"ts":93075387476},{"cat":"function","dur":238686,"name":"void __cdecl Quelos::Renderer2D::Init(class std::shared_ptr<class Quelos::UniformBuffer>)","ph":"X","pid":0,"tid":4177716615,"ts":93075191944},{"cat":"function","dur":240107,"name":"void __cdecl Quelos::Renderer::Init(void)","ph":"X","pid":0,"tid":4177716615,"ts":93075190580},{"cat":"function","dur":477,"name":"stbi_load->OpenGLTexture2D::OpenGLTexture2D(const std::string&)","ph":"X","pid":0,"tid":4177716615,"ts":93075649268},{"cat":"function","dur":10541,"name":"__cdecl Quelos::OpenGLTexture2D::OpenGLTexture2D(const class std::filesystem::path &,const struct Quelos::TextureSpecification &)","ph":"X","pid":0,"tid":4177716615,"ts":93075649240},{"cat":"function","dur":38384,"name":"stbi_load->OpenGLTexture2D::OpenGLTexture2D(const std::string&)","ph":"X","pid":0,"tid":4177716615,"ts":93075664325},{"cat":"function","dur":43074,"name":"__cdecl Quelos::OpenGLTexture2D::OpenGLTexture2D(const class std::filesystem::path &,const struct Quelos::TextureSpecification &)","ph":"X","pid":0,"tid":4177716615,"ts":93075664322},{"cat":"function","dur":24444,"name":"stbi_load->OpenGLTexture2D::OpenGLTexture2D(const std::string&)","ph":"X","pid":0,"tid":4177716615,"ts":93075714930},{"cat":"function","dur":29673,"name":"__cdecl Quelos::OpenGLTexture2D::OpenGLTexture2D(const class std::filesystem::path &,const struct Quelos::TextureSpecification &)","ph":"X","pid":0,"tid":4177716615,"ts":93075714926},{"cat":"function","dur":31621,"name":"stbi_load->OpenGLTexture2D::OpenGLTexture2D(const std::string&)","ph":"X","pid":0,"tid":4177716615,"ts":93075752475},{"cat":"function","dur":46395,"name":"__cdecl Quelos::OpenGLTexture2D::OpenGLTexture2D(const class std::filesystem::path &,const struct Quelos::TextureSpecification &)","ph":"X","pid":0,"tid":4177716615,"ts":93075752472},{"cat":"function","dur":371571,"name":"stbi_load->OpenGLTexture2D::OpenGLTexture2D(const std::string&)","ph":"X","pid":0,"tid":4177716615,"ts":93075817508},{"cat":"function","dur":431762,"name":"__cdecl Quelos::OpenGLTexture2D::OpenGLTexture2D(const class std::filesystem::path &,const struct Quelos::TextureSpecification &)","ph":"X","pid":0,"tid":4177716615,"ts":93075817504},{"cat":"function","dur":211,"name":"stbi_load->OpenGLTexture2D::OpenGLTexture2D(const std::string&)","ph":"X","pid":0,"tid":4177716615,"ts":93076318015},{"cat":"function","dur":592,"name":"__cdecl Quelos::OpenGLTexture2D::OpenGLTexture2D(const class std::filesystem::path &,const struct Quelos::TextureSpecification &)","ph":"X","pid":0,"tid":4177716615,"ts":93076318013},{"cat":"function","dur":43393,"name":"stbi_load->OpenGLTexture2D::OpenGLTexture2D(const std::string&)","ph":"X","pid":0,"tid":4177716615,"ts":93076324974},{"cat":"function","dur":50178,"name":"__cdecl Quelos::OpenGLTexture2D::OpenGLTexture2D(const class std::filesystem::path &,const struct Quelos::TextureSpecification &)","ph":"X","pid":0,"tid":4177716615,"ts":93076324970},{"cat":"function","dur":5210,"name":"void __cdecl Quelos::ImGuiLayer::OnAttach(void)","ph":"X","pid":0,"tid":4177716615,"ts":93076448879},{"cat":"function","dur":5515,"name":"void __cdecl Quelos::Application::PushOverlay(class Quelos::Layer *)","ph":"X","pid":0,"tid":4177716615,"ts":93076448868},{"cat":"function","dur":2173112,"name":"__cdecl Quelos::Application::Application(const struct Quelos::ApplicationSpecification &)","ph":"X","pid":0,"tid":4177716615,"ts":93074281431},{"cat":"function","dur":9732,"name":"stbi_load->OpenGLTexture2D::OpenGLTexture2D(const std::string&)","ph":"X","pid":0,"tid":4177716615,"ts":93076454873},{"cat":"function","dur":14498,"name":"__cdecl Quelos::OpenGLTexture2D::OpenGLTexture2D(const class std::filesystem::path &,const struct Quelos::TextureSpecification &)","ph":"X","pid":0,"tid":4177716615,"ts":93076454865},{"cat":"function","dur":48027,"name":"stbi_load->OpenGLTexture2D::OpenGLTexture2D(const std::string&)","ph":"X","pid":0,"tid":4177716615,"ts":93076469551},{"cat":"function","dur":53273,"name":"__cdecl Quelos::OpenGLTexture2D::OpenGLTexture2D(const class std::filesystem::path &,const struct Quelos::TextureSpecification &)","ph":"X","pid":0,"tid":4177716615,"ts":93076469547},{"cat":"function","dur":62675,"name":"stbi_load->OpenGLTexture2D::OpenGLTexture2D(const std::string&)","ph":"X","pid":0,"tid":4177716615,"ts":93076522917},{"cat":"function","dur":63223,"name":"__cdecl Quelos::OpenGLTexture2D::OpenGLTexture2D(const class std::filesystem::path &,const struct Quelos::TextureSpecification &)","ph":"X","pid":0,"tid":4177716615,"ts":93076522915},{"cat":"function","dur":211,"name":"class std::basic_string<char,struct std::char_traits<char>,class std::allocator<char> > __cdecl Quelos::OpenGLShader::ReadFile(const class std::basic_string<char,struct std::char_traits<char>,class std::allocator<char> > &)","ph":"X","pid":0,"tid":4177716615,"ts":93076589033},{"cat":"function","dur":72,"name":"class std::unordered_map<unsigned int,class std::basic_string<char,struct std::char_traits<char>,class std::allocator<char> >,struct std::hash<unsigned int>,struct std::equal_to<unsigned int>,class std::allocator<struct std::pair<unsigned int const ,class std::basic_string<char,struct std::char_traits<char>,class std::allocator<char> > > > > __cdecl Quelos::OpenGLShader::PreProcess(const class std::basic_string<char,struct std::char_traits<char>,class std::allocator<char> > &)","ph":"X","pid":0,"tid":4177716615,"ts":93076589434},{"cat":"function","dur":38502,"name":"__cdecl Quelos::OpenGLShader::OpenGLShader(const class std::basic_string<char,struct std::char_traits<char>,class std::allocator<char> > &)","ph":"X","pid":0,"tid":4177716615,"ts":93076588911},{"cat":"function","dur":799,"name":"class std::basic_string<char,struct std::char_traits<char>,class std::allocator<char> > __cdecl Quelos::OpenGLShader::ReadFile(const class std::basic_string<char,struct std::char_traits<char>,class std::allocator<char> > &)","ph":"X","pid":0,"tid":4177716615,"ts":93076627666},{"cat":"function","dur":66,"name":"class std::unordered_map<unsigned int,class std::basic_string<char,struct std::char_traits<char>,class std::allocator<char> >,struct std::hash<unsigned int>,struct std::equal_to<unsigned int>,class std::allocator<struct std::pair<unsigned int const ,class std::basic_string<char,struct std::char_traits<char>,class std::allocator<char> > > > > __cdecl Quelos::OpenGLShader::PreProcess(const class std::basic_string<char,struct std::char_traits<char>,class std::allocator<char> > &)","ph":"X","pid":0,"tid":4177716615,"ts":93076628563},{"cat":"function","dur":58760,"name":"__cdecl Quelos::OpenGLShader::OpenGLShader(const class std::basic_string<char,struct std::char_traits<char>,class std::allocator<char> > &)","ph":"X","pid":0,"tid":4177716615,"ts":93076627579},{"cat":"function","dur":208,"name":"class std::basic_string<char,struct std::char_traits<char>,class std::allocator<char> > __cdecl Quelos::OpenGLShader::ReadFile(const class std::basic_string<char,struct std::char_traits<char>,class std::allocator<char> > &)","ph":"X","pid":0,"tid":4177716615,"ts":93076686606},{"cat":"function","dur":58,"name":"class std::unordered_map<unsigned int,class std::basic_string<char,struct std::char_traits<char>,class std::allocator<char> >,struct std::hash<unsigned int>,struct std::equal_to<unsigned int>,class std::allocator<struct std::pair<unsigned int const ,class std::basic_string<char,struct std::char_traits<char>,class std::allocator<char> > > > > __cdecl Quelos::OpenGLShader::PreProcess(const class std::basic_string<char,struct std::char_traits<char>,class std::allocator<char> > &)","ph":"X","pid":0,"tid":4177716615,"ts":93076686888},{"cat":"function","dur":42521,"name":"__cdecl Quelos::OpenGLShader::OpenGLShader(const class std::basic_string<char,struct std::char_traits<char>,class std::allocator<char> > &)","ph":"X","pid":0,"tid":4177716615,"ts":93076686507},{"cat":"function","dur":8,"name":"__cdecl Quelos::OpenGLVertexArray::OpenGLVertexArray(void)","ph":"X","pid":0,"tid":4177716615,"ts":93076729238},{"cat":"function","dur":247,"name":"__cdecl Quelos::OpenGLVertexBuffer::OpenGLVertexBuffer(float *,unsigned int)","ph":"X","pid":0,"tid":4177716615,"ts":93076729352},{"cat":"function","dur":1,"name":"void __cdecl Quelos::OpenGLVertexBuffer::Bind(void) const","ph":"X","pid":0,"tid":4177716615,"ts":93076729722},{"cat":"function","dur":72,"name":"void __cdecl Quelos::OpenGLVertexArray::AddVertexBuffer(const class std::shared_ptr<class Quelos::VertexBuffer> &)","ph":"X","pid":0,"tid":4177716615,"ts":93076729716},{"cat":"function","dur":156,"name":"__cdecl Quelos::OpenGLIndexBuffer::OpenGLIndexBuffer(unsigned int *,unsigned int)","ph":"X","pid":0,"tid":4177716615,"ts":93076729849},{"cat":"function","dur":1,"name":"void __cdecl Quelos::OpenGLIndexBuffer::Bind(void) const","ph":"X","pid":0,"tid":4177716615,"ts":93076730112},{"cat":"function","dur":63,"name":"void __cdecl Quelos::OpenGLVertexArray::SetIndexBuffer(const class std::shared_ptr<class Quelos::IndexBuffer> &)","ph":"X","pid":0,"tid":4177716615,"ts":93076730108},{"cat":"function","dur":5,"name":"__cdecl Quelos::OpenGLVertexArray::OpenGLVertexArray(void)","ph":"X","pid":0,"tid":4177716615,"ts":93076730242},{"cat":"function","dur":1,"name":"void __cdecl Quelos::OpenGLVertexBuffer::Bind(void) const","ph":"X","pid":0,"tid":4177716615,"ts":93076730317},{"cat":"function","dur":67,"name":"void __cdecl Quelos::OpenGLVertexArray::AddVertexBuffer(const class std::shared_ptr<class Quelos::VertexBuffer> &)","ph":"X","pid":0,"tid":4177716615,"ts":93076730313},{"cat":"function","dur":1,"name":"void __cdecl Quelos::OpenGLIndexBuffer::Bind(void) const","ph":"X","pid":0,"tid":4177716615,"ts":93076730442},{"cat":"function","dur":55,"name":"void __cdecl Quelos::OpenGLVertexArray::SetIndexBuffer(const class std::shared_ptr<class Quelos::IndexBuffer> &)","ph":"X","pid":0,"tid":4177716615,"ts":93076730439},{"cat":"function","dur":925,"name":"stbi_load->OpenGLTexture2D::OpenGLTexture2D(const std::string&)","ph":"X","pid":0,"tid":4177716615,"ts":93076730800},{"cat":"function","dur":1446,"name":"__cdecl Quelos::OpenGLTexture2D::OpenGLTexture2D(const class std::filesystem::path &,const struct Quelos::TextureSpecification &)","ph":"X","pid":0,"tid":4177716615,"ts":93076730797},{"cat":"function","dur":450,"name":"stbi_load->OpenGLTexture2D::OpenGLTexture2D(const std::string&)","ph":"X","pid":0,"tid":4177716615,"ts":93076732474},{"cat":"function","dur":995,"name":"__cdecl Quelos::OpenGLTexture2D::OpenGLTexture2D(const class std::filesystem::path &,const struct Quelos::TextureSpecification &)","ph":"X","pid":0,"tid":4177716615,"ts":93076732389},{"cat":"function","dur":1223,"name":"stbi_load->OpenGLTexture2D::OpenGLTexture2D(const std::string&)","ph":"X","pid":0,"tid":4177716615,"ts":93076733566},{"cat":"function","dur":1984,"name":"__cdecl Quelos::OpenGLTexture2D::OpenGLTexture2D(const class std::filesystem::path &,const struct Quelos::TextureSpecification &)","ph":"X","pid":0,"tid":4177716615,"ts":93076733562},{"cat":"function","dur":913,"name":"stbi_load->OpenGLTexture2D::OpenGLTexture2D(const std::string&)","ph":"X","pid":0,"tid":4177716615,"ts":93076735709},{"cat":"function","dur":1412,"name":"__cdecl Quelos::OpenGLTexture2D::OpenGLTexture2D(const class std::filesystem::path &,const struct Quelos::TextureSpecification &)","ph":"X","pid":0,"tid":4177716615,"ts":93076735706},{"cat":"function","dur":15076,"name":"void __cdecl Quelos::EditorLayer::OnAttach(void)","ph":"X","pid":0,"tid":4177716615,"ts":93076730766},{"cat":"function","dur":15224,"name":"void __cdecl Quelos::Application::PushLayer(class Quelos::Layer *)","ph":"X","pid":0,"tid":4177716615,"ts":93076730748}]}